mip/__init__.py
mip/_version.py
mip/callbacks.py
mip/cbc.py
mip/conflict.py
mip/constants.py
mip/entities.py
mip/exceptions.py
mip/gurobi.py
mip/lists.py
mip/log.py
mip/model.py
mip/ndarray.py
mip/solver.py
mip/libraries/cbc-c-darwin-x86-64.dylib
mip/libraries/cbc-c-linux-x86-64.so
mip/libraries/win64/cbc-c-windows-x86-64.dll
mip/libraries/win64/libbz2-1.dll
mip/libraries/win64/libgcc_s_seh-1.dll
mip/libraries/win64/libstdc++-6.dll
mip/libraries/win64/libwinpthread-1.dll
mip-1.14.2.dist-info/LICENSE
mip-1.14.2.dist-info/METADATA
mip-1.14.2.dist-info/WHEEL
mip-1.14.2.dist-info/top_level.txt
mip-1.14.2.dist-info/RECORD
