Metadata-Version: 2.1
Name: mip
Version: 1.14.2
Summary: Python tools for Modeling and Solving Mixed-Integer Linear Programs (MIPs)
Author-email: "T.A.M. Toffolo" <haroldo.santos@gmail.com>, "H.G. Santos" <tulio@toffolo.com.br>
Maintainer-email: "S. Heger" <heger@m2p.net>
License: Eclipse Public License - v 2.0
Project-URL: Homepage, https://www.python-mip.com
Project-URL: Repository, https://github.com/coin-or/python-mip
Keywords: Optimization,Linear Programming,Integer Programming,Operations Research
Classifier: Development Status :: 5 - Production/Stable
Classifier: License :: OSI Approved :: Eclipse Public License 2.0 (EPL-2.0)
Classifier: Operating System :: OS Independent
Classifier: Programming Language :: Python :: 3
Classifier: Programming Language :: Python :: Implementation :: CPython
Classifier: Programming Language :: Python :: Implementation :: PyPy
Classifier: Topic :: Scientific/Engineering :: Mathematics
Requires-Python: >=3.7
Provides-Extra: numpy
Provides-Extra: gurobi
License-File: LICENSE
